c2casgiutils/__init__.py
c2casgiutils/auth.py
c2casgiutils/broadcast/__init__.py
c2casgiutils/broadcast/interface.py
c2casgiutils/broadcast/local.py
c2casgiutils/broadcast/redis.py
c2casgiutils/broadcast/utils.py
c2casgiutils/config.py
c2casgiutils/headers.py
c2casgiutils/health_checks.py
c2casgiutils/py.typed
c2casgiutils/redis_utils.py
c2casgiutils/scripts/genversion.py
c2casgiutils/tools/__init__.py
c2casgiutils/tools/headers.py
c2casgiutils/tools/logging_.py
c2casgiutils/tools/static/favicon-16x16.png
c2casgiutils/tools/static/favicon-32x32.png
c2casgiutils/tools/static/index.css
c2casgiutils/tools/static/index.js
c2casgiutils/tools/templates/index.html
c2casgiutils-0.6.3.dist-info/METADATA
c2casgiutils-0.6.3.dist-info/WHEEL
c2casgiutils-0.6.3.dist-info/entry_points.txt
c2casgiutils-0.6.3.dist-info/RECORD
