Metadata-Version: 2.3
Name: c2casgiutils
Version: 0.6.3
Summary: Common utilities for Camptocamp ASGI applications
License: BSD-2-Clause
Keywords: sqlalchemy,asgi,fastapi
Author: Camptocamp
Author-email: info@camptocamp.com
Requires-Python: >=3.10
Classifier: Development Status :: 5 - Production/Stable
Classifier: Environment :: Plugins
Classifier: Framework :: Pyramid
Classifier: Intended Audience :: Developers
Classifier: Intended Audience :: Information Technology
Classifier: Operating System :: OS Independent
Classifier: Programming Language :: Python
Classifier: Programming Language :: Python :: 3
Classifier: Programming Language :: Python :: 3.10
Classifier: Programming Language :: Python :: 3.11
Classifier: Programming Language :: Python :: 3.12
Classifier: Programming Language :: Python :: 3.13
Classifier: Topic :: Internet :: WWW/HTTP :: WSGI :: Application
Classifier: Typing :: Typed
Provides-Extra: alembic
Provides-Extra: all
Provides-Extra: fastapi
Provides-Extra: prometheus
Provides-Extra: sentry
Provides-Extra: sqlalchemy
Requires-Dist: aiofile
Requires-Dist: aiofiles
Requires-Dist: aiohttp
Requires-Dist: alembic ; extra == "alembic"
Requires-Dist: alembic ; extra == "all"
Requires-Dist: fastapi[standard] ; extra == "all"
Requires-Dist: fastapi[standard] ; extra == "fastapi"
Requires-Dist: prometheus-client
Requires-Dist: prometheus-fastapi-instrumentator
Requires-Dist: prometheus-fastapi-instrumentator ; extra == "all"
Requires-Dist: prometheus-fastapi-instrumentator ; extra == "prometheus"
Requires-Dist: pydantic-settings
Requires-Dist: pyjwt
Requires-Dist: redis
Requires-Dist: sentry-sdk[fastapi]
Requires-Dist: sentry-sdk[fastapi] ; extra == "all"
Requires-Dist: sentry-sdk[fastapi] ; extra == "sentry"
Requires-Dist: sqlalchemy ; extra == "alembic"
Requires-Dist: sqlalchemy ; extra == "all"
Requires-Dist: sqlalchemy ; extra == "sqlalchemy"
Project-URL: Bug Tracker, https://github.com/camptocamp/c2casgiutils/issues
Project-URL: Repository, https://github.com/camptocamp/c2casgiutils
